Metadata-Version: 2.1
Name: odoo-addon-l10n_fr_intrastat_product
Version: 18.0.1.0.0.4
Requires-Python: >=3.10
Requires-Dist: odoo-addon-intrastat_product==18.0.*
Requires-Dist: odoo-addon-l10n_fr_department==18.0.*
Requires-Dist: odoo==18.0.*
Summary: EMEBI (ex-DEB) for France
Home-page: https://github.com/OCA/l10n-france
License: AGPL-3
Author: Akretion,Odoo Community Association (OCA)
Author-email: support@odoo-community.org
Classifier: Programming Language :: Python
Classifier: Framework :: Odoo
Classifier: Framework :: Odoo :: 18.0
Classifier: License :: OSI Approved :: GNU Affero General Public License v3
